NEmusicApi/__init__.py
NEmusicApi/api.py
NEmusicApi/exception.py
NEmusicApi/rawapi.py
NEmusicApi/type.py
nemusicapi-0.1.2.dist-info/LICENSE
nemusicapi-0.1.2.dist-info/METADATA
nemusicapi-0.1.2.dist-info/WHEEL
nemusicapi-0.1.2.dist-info/RECORD
