Metadata-Version: 2.1
Name: nemusicapi
Version: 0.1.2
Summary: 一个网易云音乐的Api框架
Home-page: https://github.com/yuyi2439/NEmusicApi-python
License: MIT
Author: yuyi2439
Requires-Python: >=3.9,<4.0
Classifier: License :: OSI Approved :: MIT License
Classifier: Programming Language :: Python :: 3
Classifier: Programming Language :: Python :: 3.9
Classifier: Programming Language :: Python :: 3.10
Classifier: Programming Language :: Python :: 3.11
Requires-Dist: pycryptodome (>=3.18.0,<4.0.0)
Requires-Dist: requests (>=2.31.0,<3.0.0)
Project-URL: Repository, https://github.com/yuyi2439/NEmusicApi-python
